preownedgpt/__init__.py
preownedgpt-0.0.2.dist-info/METADATA
preownedgpt-0.0.2.dist-info/WHEEL
preownedgpt-0.0.2.dist-info/RECORD
