Metadata-Version: 2.4
Name: preownedgpt
Version: 0.0.2
Summary: Placeholder package that redirects to the PreownedGPT website.
Project-URL: Homepage, https://preownedgpt.com
Project-URL: Source, https://preownedgpt.com
Project-URL: Issues, https://preownedgpt.com
Author-email: PreownedGPT <hello@preownedgpt.com>
License: MIT
Keywords: placeholder,redirect
Classifier: License :: OSI Approved :: MIT License
Classifier: Operating System :: OS Independent
Classifier: Programming Language :: Python :: 3
Requires-Python: >=3.8
